{
	"Ads": [{
		"select_main_ads": "ADMOB",
		"select_backup_ads": "STARTAPP",
		"main_ads_banner": "ca-app-pub-8359503984668545/5569391454",
		"main_ads_intertitial": "ca-app-pub-8359503984668545/3853835162",
		"backup_ads_banner": "qwerty1234",
		"backup_ads_intertitial": "qwerty1234",
		"interval_intertitial": 3,
		"initialize_sdk": "211751235",
		"initialize_sdk_backup_ads": "211751235",
		"high_paying_keyword_1": "",
		"high_paying_keyword_2": "",
		"high_paying_keyword_3": "",
		"high_paying_keyword_4": "",
		"high_paying_keyword_5": "",
		"status_app": "0",
		"link_redirect": "https://"
	}],
	"Categories": [{
			"id": 1,
			"name_category": "ENHYPEN BEST SONG",
			"image": "file:///android_asset/image/anyar.jpg"
		}


	],
	"Data": [{
			"id": 1,
			"name_category": "ENHYPEN BEST SONG",
			"title": "10 Months",
			"image": "file:///android_asset/image/anyar.jpg",
			"link_mp3": "mp3/10Months.mp3",
			"duration": "249",
			"lyrics": "<br/>Ijen da keonneunde<br/>Wae jakku ae chwigeupae<br/>Jeongmal keotdaneunde<br/>Oh yeah<br/><br/>Kiman keun ge anya<br/>Gwiyeopda jom haji ma<br/>Geu useumeun mwonde<br/><br/>Got alge doel geoya<br/>Gangaji chwigeupajiman<br/>All day all night<br/><br/>Naeilbuteon naega<br/>Naega neol jikyeojul geoya<br/>All day all night<br/><br/>Ja ijen naege gidae jeongmallo<br/>Ijen naege gidae jeongmallo<br/>Wae neon utgiman hae nae mameul mollajwo wae neon<br/>Ijen naege gidae jeongmal<br/>Ijen naege gidae jeongmal<br/>Love love<br/>Love love<br/>My 10 months' love<br/><br/>Seotureun nae momjisi<br/>Jogeum eorin nae maltuga<br/>Mideopjaneun geol ara<br/><br/>Hajiman gidaryeo<br/>Kimankeum mamdo jaraseo<br/>All day all night<br/><br/>Naeilbuteon naega<br/>Naega neol jikyeojul geoya<br/>All day all night<br/><br/>Ja ijen naege gidae jeongmallo<br/>Ijen naege gidae jeongmallo<br/>Wae neon utgiman hae nae mameul mollajwo wae neon<br/>Ijen naege gidae jeongmal<br/>Ijen naege gidae jeongmal<br/>Love love<br/>Love love<br/>My 10 months' love love<br/>Love love<br/>My 10 months' love<br/><br/>Meotjige byeonhalge<br/>Woo love nege eoullige<br/>Neoman injeonghae jumyeon dwae<br/><br/>Ja ijen naege gidae jeongmallo<br/>Ijen naege gidae jeongmallo<br/>Wae neon utgiman hae nae mameul mollajwo wae neon<br/>Ijen naege gidae jeongmal<br/>Ijen naege gidae jeongmal<br/>Love love<br/>Love love<br/>My 10 months' love love<br/>Love love<br/>My 10 months' love<br/>"
		},
		{
			"id": 2,
			"name_category": "ENHYPEN BEST SONG",
			"title": "ATTENTION PLEASE",
			"image": "file:///android_asset/image/anyar.jpg",
			"link_mp3": "mp3/ATTENTIONPLEASE.mp3",
			"duration": "233",
			"lyrics": "<br/>Say what you want nal barabwa<br/>Nan mugwansimeun sayanghae<br/>Modu nal wonhagil wonhae<br/>Geujunge teuki ne mameul<br/><br/>Yeogiseo jjuk neoman bogo itjana<br/>Inssa junge inssain nareul jom bwa bwa<br/>Meonjeo dagagal yonggineun eopjiman<br/>Arachae jugil neoreul hyanghan nae mameul<br/><br/>Moduga nal barabwa jwo<br/>Ingiwa sarang nan jeonbu da gatgo sipeo<br/>Oh no-oh-ooh-oh! I don't know what to do<br/>Kkoyeobeorin kkum (Let's go!)<br/><br/>Attention please!<br/>Modu nal jumokae<br/>Ssak da nal jumokae<br/>Get it, get it<br/>Geunde daeche neoneun wae<br/>Nareul mot bon cheokae<br/>Wae tto mot bon cheokae<br/>Panic, panic<br/><br/>(Here we go-oh-oh)<br/>Gallimgire seoseo (yeogi seoseo)<br/>Kkomjjak mot hae nan (guhaejwo na jom)<br/>Dillemae ppajyeo (ireodaga)<br/>Jinjja jeonbu da ileulkka geomna<br/><br/>Neureonan follow and heart (joayo kkuk)<br/>Nae kkumgwa gakkawojilsurok<br/>Neowaneun jeomjeom meoreojineun neukkim<br/>Budamseureopgo mak geureotae<br/><br/>Moduga nal barabwa jwo<br/>Ingiwa sarang nan jeonbu da gatgo sipeo<br/>Oh no-oh-ooh-oh! I don't know what to do<br/>Kkoyeobeorin kkum (Let's go!)<br/><br/>Attention please!<br/>Modu nal jumokae<br/>Ssak da nal jumokae<br/>Get it, get it<br/>Geunde daeche neoneun wae<br/>Nareul mot bon cheokae<br/>Wae tto mot bon cheokae<br/>Panic, panic<br/><br/>(Here we go-oh-oh)<br/>Gallimgire seoseo (yeogi seoseo)<br/>Kkomjjak mot hae nan (guhaejwo na jom)<br/>Dillemae ppajyeo (ireodaga)<br/>Jinjja jeonbu da ileulkka geomna<br/><br/>(Let's go!)<br/>Attention please!<br/>Modu nal jumokae<br/>Ssak da nal jumokae<br/>Get it, get it<br/>Geunde daeche neoneun wae<br/>Nareul mot bon cheokae<br/>Wae tto mot bon cheokae<br/>Panic, panic<br/><br/><br/>(Here we go-oh-oh)<br/>Gallimgire seoseo (yeogi seoseo)<br/>Kkomjjak mot hae nan (guhaejwo na jom)<br/>Dillemae ppajyeo (ireodaga)<br/>Jinjja jeonbu da ileulkka geomna<br/>"
		},
		{
			"id": 3,
			"name_category": "ENHYPEN BEST SONG",
			"title": "Chamber5_Dream of Dream",
			"image": "file:///android_asset/image/anyar.jpg",
			"link_mp3": "mp3/Chamber5_DreamofDream.mp3",
			"duration": "198",
			"lyrics": "<br/>Do do do do do you ever?<br/>Do do do do do you ever?<br/>Do do do do do you ever?<br/>Do do do do do you ever?<br/><br/>Nuneul gamasseo allyeogo hajido anhasseo<br/>Kkumilan geu geuljaga nunmeolge halkka bwa<br/>Gaseumi ttwieodo moleun cheog haesseo naega miwodo<br/>Gajji moshal baeya balajido anheulyeo<br/><br/>But now teojil deushan i gibun whoo whoo<br/>Sumgyeo-on kkum<br/>I nal dageuchideut deonjin jilmun whoo whoo<br/>Do do do do do you ever?<br/><br/>Nae mam gajang anjjog e jala<br/>Keojyeo beolin Chamber 5<br/><br/>Geu bang<br/>Sumgyeoon bimil<br/>Daedab!<br/>Do you ever dream of dreams?<br/><br/>Of dream of dream of dream of dream of dreams yeah<br/>Of dream of dream of dreams<br/>Do you ever dream of dreams?<br/><br/>Of dream of dream of dream of dream of dream yeah<br/>Of dream of dream of dreams<br/>Do you ever dream of dreams?<br/><br/>Naegen maliya machi daia gateun kkumi issda maliya<br/>Gamchwodo bichi na sumgil su eobsiji<br/>Nae mamsog gipi nal jitaenghaji<br/>Simbanggwa simsil ioe naui daseot beonjjae bang<br/>Geugoseun jalanan kkumui geocheo bimului bang<br/><br/>So now hyeonsili doen singilu whoo whoo<br/>My dreams come true<br/>That's right aleumdawo pyeolchyeojin view whoo whoo<br/>Do do do do do you ever?<br/><br/>Mihoge hollyeoseo eodumeul hemaesseo bicheul oemyeonhae meolli domangchyeosseo<br/>Hajiman chajanaen bimului bange dulyeoume ppajyeo gadun naleul guhae<br/><br/>Nae mam gajang anjjog e jala<br/>Keojyeo beolin Chamber 5<br/><br/>Geu bang<br/>Sumgyeoon bimil<br/>Daedab!<br/>Do you ever dream of dreams?<br/><br/>Of dream of dream of dream of dream of dreams yeah<br/>Of dream of dream of dreams<br/>Do you ever dream of dreams?<br/><br/>Of dream of dream of dream of dream of dreams yeah<br/>Of dream of dream of dreams<br/>Do you ever dream of dreams?<br/>"
		},
		{
			"id": 4,
			"name_category": "ENHYPEN BEST SONG",
			"title": "Drunk Dazed",
			"image": "file:///android_asset/image/anyar.jpg",
			"link_mp3": "mp3/DrunkDazed.mp3",
			"duration": "222",
			"lyrics": "<br/>Areumdapgo hwangholhae<br/>Banjjagineun nae gangmageun daiamondeu<br/>Gyuchik eomneun segyeneun<br/>Jeonbu dwijipyeo dwijipyeo seoisseo<br/><br/>Turning up the party, now<br/>Haneuren nae bari, Wow<br/>Saramdeureun Ha ha, high<br/>Nae gwitsogeneun La la, loud<br/>Nunbusyeo, Baby<br/>I jomyeong, Shining<br/>We're in love with this carnival<br/><br/>Sasil museowo nan<br/>Chulleongineun jansok i chwihan segye<br/>Geu kkeuten mogi taneun nae mam<br/>But I just wanna stay<br/><br/>Neukkyeojyeo, nae meorin Daze, daze, daze<br/>Jungdoge ppajyeo Replay, play, play<br/>Wonham wonhaneun daero<br/>Gal ttaekkaji gabwa Go<br/>Nareul gadun Carnival wow, wow<br/>Dasi nae simjangi Daze, daze, daze<br/>Can't control my body dance, dance, dance<br/>Dalkomhan i hyanggido<br/>Bulgeunbit songgonnido<br/>Jeulgyeobwa, i Carnival wow, wow<br/><br/>Mmm gyeonggyeseoneul neomeo nal bulleo nal<br/>Modeun geosi bakkwieo, modu muneojyeo<br/>Jamgin mun neomeo son ppeodeo nan<br/>Gotongi nal bangyeo, galjeungui hyangyeon<br/><br/>Sasil duryeowo nan<br/>Geoul sogui naega natseolgiman hae<br/>I gamyeon dwi chorahan jinsil<br/>But I never escape<br/><br/>Neukkyeojyeo, nae meorin Daze, daze, daze<br/>Jungdoge ppajyeo Replay, play, play<br/>Wonham wonhaneun daero<br/>Gal ttaekkaji gabwa Go<br/>Nareul gadun Carnival wow, wow<br/>Dasi nae simjangi Daze, daze, daze<br/>Can't control my body dance, dance, dance<br/>Dalkomhan i hyanggido<br/>Bulgeunbit songgonnido<br/>Jeulgyeobwa, i Carnival wow, wow<br/><br/>Naege jueojin geu bit<br/>Seonghwaui bulgil Ah<br/>Juini doel ttaekkaji Imma ride<br/><br/>Neukkyeojyeo, nae meorin Daze, daze, daze<br/>Jungdoge ppajyeo Replay, play, play<br/>Wonham wonhaneun daero<br/>Gal ttaekkaji gabwa Go<br/>Nareul gadun Carnival wow, wow<br/>Dasi nae simjangi Daze, daze, daze<br/>Can't control my body dance, dance, dance<br/>Dalkomhan i hyanggido<br/>Bulgeunbit songgonnido<br/>Jeulgyeobwa, i Carnival wow, wow<br/><br/>Nan nareul kkaewo<br/>Simjangeul taewo<br/>Nae kkumeul chaewo<br/>Nan nareul kkaewo<br/>Simjangeul taewo<br/>Nae kkumeul chaewo<br/>"
		},
		{
			"id": 5,
			"name_category": "ENHYPEN BEST SONG",
			"title": "FEVER",
			"image": "file:///android_asset/image/anyar.jpg",
			"link_mp3": "mp3/FEVER.mp3",
			"duration": "255",
			"lyrics": "<br/><br/>Give me fever<br/><br/>Eoreum gateun nun, geu bulgeun nunbit<br/>Breaking me in two, nareul heundeulji<br/>Wangjwae anjeun ne ape seol ttae<br/>Nae ane taneun bulgil<br/><br/>What I gotta do, tteugeoun soni<br/>Neoreul chajado I cannot have it<br/>Neoege sondaeseon an dwae, jeoldae<br/>Hajiman ikkeulliji<br/>Nan apeulsurok neol wonhae<br/><br/>Meomchwo jebal, meomchuji ma<br/>Meomchwo jebal, meomchuji ma (Ah)<br/><br/>Neo ttaemune onmomi taolla<br/>Neo ttaemune simjangi mongmalla<br/>Like a fever, fever, fever, fever<br/>Neol ango sipeo<br/>Neol ango sipeo<br/>Mireonaedo nae ane taolla<br/>Jaega dwaedo bulkkochi pieona<br/>Like a fever, fever, fever<br/>Neol alko sipeo<br/>Neol alko sipeo<br/><br/>Don't stop! (Stop!)<br/>Geurae all day, all day taewojwo<br/>Please stop! (Stop!)<br/>Naui taeyangiyeo geuman Baby, oh baby (Ooo)<br/>Ireon nal eotteoke jom haejwo eotteoke jom nal<br/><br/>Nal noajwo nal anajwo<br/>Nal noajwo nal anajwo<br/><br/>Neo ttaemune onmomi taolla<br/>Neo ttaemune simjangi mongmalla<br/>Like a fever, fever, fever, fever<br/>Neol ango sipeo<br/>Neol ango sipeo<br/>Mireonaedo nae ane taolla<br/>Jaega dwaedo bulkkochi pieona<br/>Like a fever, fever, fever<br/>Neol alko sipeo<br/>Neol alko sipeo<br/><br/>Neo ttaemune onmomi taolla<br/>Neo ttaemune simjangi mongmalla<br/>Like a fever, fever, fever, fever<br/>Neol ango sipeo<br/>Neol ango sipeo<br/>Mireonaedo nae ane taolla<br/>Jaega dwaedo bulkkochi pieona<br/>Like a fever, fever, fever<br/>Neol alko sipeo<br/>Neol alko sipeo<br/>"
		},
		{
			"id": 6,
			"name_category": "ENHYPEN BEST SONG",
			"title": "FLICKER",
			"image": "file:///android_asset/image/anyar.jpg",
			"link_mp3": "mp3/FLICKER.mp3",
			"duration": "222",
			"lyrics": "<br/>Urin maeil gachi seororeul chaja hemaeeo on geot gata<br/>Jeonhyeo dareun gonggan neomeo seoro maju bwa on geot gata<br/><br/>Adeuki meonameon goseseo (yeah ye)<br/>Sueopsi maneun bam geonneoseo<br/><br/>Sinhoreul bonaego arabwa jul neol gidaryeo<br/>Yaksogui eoneoro nega nal chajeul su itge<br/>Malhaji anado neowa naman al su inneun signal<br/>Eogeunna itdeon segyereul yeongyeolhaneun geoya<br/>Kkamppagineun sungan<br/><br/>Neon neukkyeo deo deo neukkyeo neukkyeo neon neon<br/>Kkamppagineun geu sungan<br/>Nan neukkyeo deo deo neukkyeo neukkyeo neol neol<br/>Ieojineun neowa na<br/><br/>Neon neukkyeo deo deo neukkyeo neukkyeo neon neon<br/>Kkamppagineun geu sungan<br/>Nan neukkyeo deo deo neukkyeo neukkyeo neol neol<br/>Ieojineun neowa na<br/><br/>Seoro dachi anado neowa nan machi hanain geonman gata (babe)<br/>Meolli isseodo eolkyeojyeo ssangeul iruneun yangja gata<br/>Sigangwa gongganeul neomeoseo (yeah ye)<br/>Nunbitgwa nunbichi ieojyeo<br/><br/>Sinhoreul bonaego arabwa jul neol gidaryeo<br/>Yaksogui eoneoro nega nal chajeul su itge<br/>Malhaji anado neowa naman al su inneun signal<br/>Eogeunna itdeon segyereul yeongyeolhaneun geoya<br/>Kkamppagineun sungan<br/><br/>Neon neukkyeo deo deo neukkyeo neukkyeo neon neon<br/>Kkamppagineun geu sungan<br/>Nan neukkyeo deo deo neukkyeo neukkyeo neol neol<br/>Ieojineun neowa na<br/><br/>Neon neukkyeo deo deo neukkyeo neukkyeo neon neon<br/>Kkamppagineun geu sungan<br/>Nan neukkyeo deo deo neukkyeo neukkyeo neol neol<br/>Ieojineun neowa na<br/>"
		},
		{
			"id": 7,
			"name_category": "ENHYPEN BEST SONG",
			"title": "FORGET ME NOT",
			"image": "file:///android_asset/image/anyar.jpg",
			"link_mp3": "mp3/FORGETMENOT.mp3",
			"duration": "266",
			"lyrics": "<br/>Kinō to chigau jibun e<br/>Kyō no sora e sakebe<br/>Ashita no kibō daite<br/>Kono mune ni Forget Me Not<br/><br/>Natsunonioi ni mezameta ano hi no kanjō<br/>Kirameku hizashi ga supīdo age tōrisugiru<br/>Yowa-sa ni tōzakatte ku tsugi hagi-darake no kyō o<br/>Ato ikutsu kurikaeshitara ashita ga kuru ndarou<br/><br/>Kumo ga kakushita keshiki wa chigatte mo<br/>Kasuka ni mune ni nokotteru kizashi shinjite<br/><br/>Omoi no take koete yuke<br/>Isshun ni tsumekon datte<br/>Todokanai gunjō no sora bokura motome teru<br/>Omoi no take naita-bun dake<br/>Kono-goe ga tsukiru made<br/>Mae ni susumu to sakebu yo<br/>Mihatenuyume no tsudzuki Forget Me Not<br/><br/>Ame no nioi ga chikadzuku naze ka setsunakute<br/>Sugiyukunatsu no gogo torinokosa reta mama no boku<br/>Michinakimichi kakiwakete susumu saki de<br/>Don'na mirai mitsukeru nda kke?<br/>Ato ikutsu fuan kazoetara niji ga mieru ndarou<br/><br/>Haruka tōku ni kasunda gōru demo<br/>Tashikani mune no oku tomosu yuragi kanjite<br/><br/>Omoi no take koete yuke<br/>Isshun ni tsumekon datte<br/>Todokanai gunjō no sora bokura motome teru<br/>Omoi no take naita-bun dake<br/>Kono-goe ga tsukiru made<br/>Mae ni susumu to sakebu yo<br/>Mihatenuyume no tsudzuki Forget Me Not<br/><br/>Maki modosenai toki no naka de soredemo tada mogaku yo<br/>Kimerareta kotae nante soko ni kachi wanai<br/>Tatoe ima wa mienakute mo itsuka hikari wa sasu<br/>Sono shunkan ni mukatte te o nobase<br/><br/>Omoi no take koete yuke<br/>Isshun ni tsumekon datte<br/>Todokanai gunjō no sora bokura motome teru<br/>Omoi no take naita-bun dake<br/>Kono-goe ga tsukiru made<br/>Mae ni susumu to sakebu yo<br/>Mihatenuyume no tsudzuki Forget Me Not<br/><br/>Kinō to chigau jibun e Yeah<br/>Kyō no sora e sakebe<br/>Ashita no kibō daite<br/>Kono mune ni Forget Me Not<br/>"
		},
		{
			"id": 8,
			"name_category": "ENHYPEN BEST SONG",
			"title": "Given Taken",
			"image": "file:///android_asset/image/anyar.jpg",
			"link_mp3": "mp3/GivenTaken.mp3",
			"duration": "228",
			"lyrics": "<br/>Wake up in day one<br/>Cheonnare achim<br/>Jomyeongi bichweo<br/>Taeyange nunbit<br/><br/>Geu bicheun nal bultaeweotji<br/>Geu bicheun naye nun garyeotji<br/>But I go now kkumeul jocha<br/>Dive into red sun, no lie<br/><br/>Sumaneun stars sumaneun dal<br/>Jilmune supsogeul hemaedeon na<br/>Eodum soge jeo bicheul ttarawasseo<br/><br/>Ganeun seon neomeoye nal bureuneun neo<br/>Neol bureuneun na<br/><br/>(To you)<br/>Unmyeonge hwasal bi sogeseo<br/>(To)<br/>Majuhan nae ane gyeonggyeseon<br/>(Free)<br/>Given or taken oh<br/>Naye bulgeun nunbit<br/>(To you)<br/>Nan ije sesangeul dwijibeo<br/>(To)<br/>Haneure nae bareul naedidyeo<br/>(Me)<br/>Given or taken oh<br/>Nae hayan songgonni<br/><br/>Oh nan neoege georeogaji<br/>Du segyereul yeongyeolhaji<br/>Naye bulgeun nunbit<br/><br/>Oh nan neoege georeogaji<br/>Shinsegyee daeul ttaekkaji<br/>Nae hayan songgonni<br/><br/>Nae dwien sucheon gaeye uishim<br/>Nae dwien suman gaeye bulshin<br/>But I go now kkumeul jocha<br/>Drive through the question for life<br/><br/>Jueojimgwa jaengchwiham sai<br/>Jeungmyeonge giro wi namgyeojin na<br/>Jeo haneureul urin gidaryeowasseo<br/><br/>Ganeun seon neomeoye nal bureuneun neo<br/>Neol bureuneun na<br/><br/>To you<br/>Unmyeonge hwasal bi sogeseo<br/>To<br/>Majuhan nae ane gyeonggyeseon<br/>(Free)<br/>Given or taken oh<br/>Naye bulgeun nunbit<br/><br/>To you<br/>Nan ije sesangeul dwijibeo<br/>To<br/>Haneure nae bareul naedidyeo<br/>Me<br/>Given or taken oh<br/>Nae hayan songgonni<br/><br/>Red blood<br/>Jeo wanggwane<br/>That blood<br/>Heureuneun pi<br/>Red blood<br/><br/>Neol hyanghan nae sonkkeucheun bulgeunbiche muldeureoman ga<br/>But I'm gonna go<br/>To you<br/>Unmyeonge hwasal bi sogeseo<br/>To<br/>Majuhan nae ane gyeonggyeseon<br/>(Free)<br/>Given or taken oh<br/>Naye bulgeun nunbit<br/><br/>To you<br/>Nan ije sesangeul dwijibeo<br/>To<br/>Haneure nae bareul naedidyeo<br/>(Me)<br/>Given or taken oh<br/>Nae hayan songgonni<br/><br/>Oh nan neoege georeogaji<br/>Du segyereul yeongyeolhaji<br/>Naye bulgeun nunbit<br/><br/>Oh nan neoege georeogaji<br/>Shinsegyee daeul ttaekkaji<br/>Nae hayan songgonni<br/>"
		},
		{
			"id": 9,
			"name_category": "ENHYPEN BEST SONG",
			"title": "Blessed Cursed",
			"image": "file:///android_asset/image/anyar.jpg",
			"link_mp3": "mp3/BlessedCursed.mp3",
			"duration": "225",
			"lyrics": "<br/>Wake up, ije nuneul tteo<br/>Gatja chukbok sogeseo<br/>I wanna be wanna be on my way, I bet<br/><br/>Nal gaduneun gyeonggyeseon<br/>Ne rul ttawin jibeochiweo<br/>I wanna be wanna I, way, I bet<br/><br/>Kkeojin jul arasseo, nae mamsok tadeon yeoreumi<br/>Dalkomhan ibsullo nal gildeurin i Property<br/>Mome geolchin Luxury, Blue pill gachi naye nun garine<br/>Tell me, do I get blessed or do I get cursed?<br/>I just want to know<br/><br/>Yusangachi geonnejin seungni, jomyeong dwie gamchweojin bimil<br/>Marioneteuye sagak aneseo chumeul chudeon nayeosseo<br/>Don't wanna stay, ije kkaedareun jinshiri<br/>Nareul bulleo, meolliseo nareul bulleo (Let's go)<br/><br/>Just stop, don't tell me what to do<br/>Hunjang gateun jeoju<br/>I jeoju soge, I'll be ok, no pain, no pain<br/><br/>Jeo bit neomeoye Liar, urin hyeonshillo Fade in<br/>I geojitteul sai, hyeonsaeng sogeuro daibing<br/>And I walk like a lion, nae yeoksareul nan Making<br/>Molla jeongdab ttawin, nae bangshikdaero gaji<br/>Goes on and on<br/><br/>Wake up, ije nuneul tteo<br/>Gatja chukbok sogeseo<br/>I wanna be wanna be on my way, I bet<br/><br/>Nal gaduneun gyeonggyeseon<br/>Ne rul ttawin jibeochiweo<br/>I wanna be wanna I, way, I bet<br/><br/>I don't want, I don't want<br/>Yeongjeom jjari geu jeongdab<br/>Ije nan itji ana<br/>Nalgaereul kkeokkeonoeun geu Lie<br/><br/>Don't wanna miss, ajik sum shwineun nadaumi<br/>Nareul bulleo, meolliseo nareul bulleo (Let's go)<br/><br/>Just stop, don't tell me what to do<br/>Hunjang gateun jeoju<br/>I jeoju soge, I'll be ok, no pain, no pain<br/><br/>Jeo bit neomeoye Liar, urin hyeonshillo Fade in<br/>I geojitteul sai, hyeonsaeng sogeuro daibing<br/>And I walk like a lion, nae yeoksareul nan Making<br/>Molla jeongdab ttawin, nae bangshikdaero gaji<br/>Goes on and on<br/><br/>Wake up, ije nuneul tteo<br/>Gatja chukbok sogeseo<br/>I wanna be wanna be on my way, I bet<br/><br/>Nal gaduneun gyeonggyeseon<br/>Ne rul ttawin jibeochiweo<br/>I wanna be wanna I, way, I bet"
		},
		{
			"id": 10,
			"name_category": "ENHYPEN BEST SONG",
			"title": "HAYEOGA",
			"image": "file:///android_asset/image/anyar.jpg",
			"link_mp3": "mp3/HAYEOGA.mp3",
			"duration": "198",
			"lyrics": "<br/>neoege modeungeol ppaesgyeobeoryeossdeon maeumi dasi naege<br/>doraoneungeol neukkyeossji<br/>neoneun eonjekkajina namanui naui yeoninira mideowassdeon<br/>nae saenggageun teulligo marasseo<br/>byeonhaebeoringeon piryoga eopseo<br/>ijeneun neoreul bwado amureon neukkimi eopseo<br/>naege hangsang siseoneul meomchwossdeon<br/>yejeonui ne moseupgwa nareul barabomyeon<br/>ne misowa neomanui moksori<br/>modeunge geuriwo jingeoya jigeum naegen<br/>neoreul bolttaemada naegen gaseumi tteollineun geu<br/>neukkimi isseossji nan geunyang nege nareul deonjingeoya<br/>ye ye ye ye ye<br/><br/>nahollo isseulttaejocha neoreul gidarindaneun<br/>seolleime eonjena gippeuge maeumeul gajyeossdeongeoya<br/>ye ye ye ye ye<br/><br/>bupureun nae mamsoge hangsang nega isseosseo<br/>hayan misoe neoreul gadeuk angoseo ijeneun<br/>neoreul wihae namgyeodun geosi isseo<br/>hae malkdeon ne misoga damgin sajineul<br/>nan geunyang idaero dwidora ganeunga<br/>neon geunyang idaero nal ijeobeorina<br/>nan geunyang idaero dwidora ganeunga<br/>neol geunyang idaero bonaegin nae gaseumi neomuna<br/>nan geunyang idaero nal ijeobeorina<br/>nan geunyang idaero nan geunyang idaero<br/>bonaegin nae gaseumi neomuna<br/><br/>Seo Taiji and Boys při comebacku s Comeback home<br/>neoege manheungeol baraneunge aniji<br/>geujeonttaecheoreom baro geuttaecheoreom mariya<br/>jeongseonghi gadeugi isseossji<br/>eonjena nareul neomu ttatteushage daehae jueossji<br/>ijeneun jeonhwareul nege ganeungeo majeo<br/>nan ije moduga duryeowo jyeosseo<br/>neon anincheokhagoneun issjiman neoui moksoriga<br/>neomudo chagapji, nan alsuga isseo<br/>neodo manhi apahago isseossdaneun geosmaneul<br/>neoui jinsimeul sumgijima neon wae geuri moreuji?<br/>neoreul bolttaemada naegen gaseumi tteollineun geu<br/>neukkimi isseossji nan geunyang nege nareul deonjingeoya<br/>ye ye ye ye ye<br/><br/>nahollo isseulttaejocha neoreul gidarindaneun<br/>seolleime eonjena gippeuge maeumeul gajyeossdeongeoya<br/>ye ye ye ye ye<br/>bupureun nae mamsoge hangsang nega isseosseo<br/>hayan misoe neoreul gadeuk angoseo ijeneun<br/>neoreul wihae namgyeodun geosi isseo<br/>hae malkdeon ne misoga damgin sajineul<br/>nan geunyang idaero dwidora ganeunga<br/>neon geunyang idaero nal ijeobeorina<br/>nan geunyang idaero dwidora ganeunga<br/>neol geunyang idaero bonaegin nae gaseumi neomuna<br/>nan geunyang idaero nal ijeobeorina<br/>nan geunyang idaero nan geunyang idaero<br/>bonaegin nae gaseumi neomuna<br/>ireohge tteonaga beorin neoreul boreohaneungeosi aniya<br/>hajiman nan gidaryeo niga dasi doraol ttaekkaji<br/>igoseseo<br/>"
		},
		{
			"id": 11,
			"name_category": "ENHYPEN BEST SONG",
			"title": "HEY TAYO",
			"image": "file:///android_asset/image/anyar.jpg",
			"link_mp3": "mp3/HEYTAYO.mp3",
			"duration": "230",
			"lyrics": "<br/><br/>(Super Genius) Okay<br/><br/>Tayotayo tayotayo gaegujaengi kkoma beoseu<br/>Bungbungbung ssingssingssing dallineun ge neomu joa<br/>Tayotayo tayotayo gaegujaengi kkoma beoseu<br/>Bungbungbung ssingssingssing hamkke gaja jaeminneun yeohaeng<br/><br/>Kkobulkkobul ultungbultung heomhan gildo duryeopji ana<br/>Eodukeomkeom kkeuchi eomneun gin teoneoldo<br/>Chinguwa hamkkeramyeon eonjena jeulgeowo<br/><br/>Tayotayo tayotayo gaegujaengi kkoma beoseu<br/>Bungbungbung ssingssingssing dallineun ge neomu joa<br/>Tayotayo tayotayo gaegujaengi kkoma beoseu<br/>Ttittitti ppangppangppang nae gyeoteneun joeun chingudeul<br/><br/>Bichinaneun diseukobol arae urihamkke chumeul jwo<br/>Put your hands up<br/>Oneulcheoreom sinnaneun nare party<br/>Junbidwaesseum sorijilleo<br/><br/>Kkobulkkobul ultungbultung heomhan gildo duryeopji ana<br/>Eodukeomkeom kkeuchi eomneun gin teoneoldo<br/>Chinguwa hamkkeramyeon eonjena jeulgeowo<br/><br/>Tayotayo tayotayo gaegujaengi kkoma beoseu<br/>Bungbungbung ssingssingssing dallineun ge neomu joa<br/>Tayotayo tayotayo gaegujaengi kkoma beoseu<br/>Ttittitti ppangppangppang nae gyeoteneun joeun chingudeul<br/>Haha hoho oneuldo sinnaneun haru<br/>"
		},
		{
			"id": 12,
			"name_category": "ENHYPEN BEST SONG",
			"title": "I LIKE IT",
			"image": "file:///android_asset/image/anyar.jpg",
			"link_mp3": "mp3/ILIKEIT.mp3",
			"duration": "240",
			"lyrics": "<br/>Wanna be loved<br/><br/>Don't wanna be fool wanna be cool<br/>Wanna be loved neowaui same love<br/>Baby I want it<br/><br/>Niga ollineun modeun sajinmada<br/>Johayo nambalhaneun cheoeum boneun jeo namja<br/>Nuguya<br/>A matda na ije namjachingu aniji<br/>Jayeonseure ni beonho nulleotjanha<br/>Jeonhwana katokhajani kkok jineun geot gatgo<br/>Mworado an hamyeon<br/>Nal singyeongdo an sseul geot gateo<br/>Wae sirheoyo beoteuneun eomneunde<br/>Sirheo jeo<br/>Samsip myeot myeong jung hanaga doeneun ge<br/>Yeogido jotago jeogido jotago<br/>Hanbeonman noljago<br/>Wae geuri gomnyago<br/>Uh fuck that all stupid bullshits<br/>Ijen nae kkeodo aninde<br/>Wae ppaetgineun geot gateunji<br/>Haha neon na eobsi cham jal sane<br/>Nunkkol siryeounikka noneun geot jom salsalhae<br/>Mokkkaji ollaon jeojureul samkigo<br/>Oneuldo johayoreul nureuji shit<br/><br/>Neon nami doego ohiryeo deo joha boyeo pretty woman<br/>Yeah yeah yeah yeah<br/>O yalmipgedo yeojeonhi neon joha boyeo pretty woman<br/>Oh pretty woman<br/><br/>Don't wanna be fool wanna be cool<br/>Wanna be loved neowaui same love<br/>I know it's over<br/>Don't wanna be fool wanna be cool<br/>Wanna be loved neowaui same love<br/>Baby I want it<br/><br/>Chingu nomi nureun johayoro<br/>Boineun ni eolgureun hwolssin joha boyeo<br/>Sae namchingwa jjigeun sajin sok tag tag<br/>Deokbune chueok sogeuro nan backspace<br/>Geu sesangeun eoneusae dadeul meomchwoinneunde<br/>Nan wae yeojeonhi geu sigane geolchyeoinneunde<br/>Ha neon nae saenggageul halkka halkka<br/>Gominhamyeo johayoreul nureulkka malkka<br/>Susip beoneul banbokhae<br/>Neoui maeumeun machi dandudaecheoreom<br/>Nareul ssakduk gachaeobsi jallanaetjiman<br/>Nan dokkaebi gamtu mollae dagaga<br/>Neoui ilsangsaenghwareul maennal bone<br/>Geuttaemada meorissogeun baekpalbeonnoe<br/>Oh shit nae saenggageun halkka halkka<br/>Gominhamyeo johayoreul nureuji malja<br/><br/>Neon nami doego ohiryeo deo joha boyeo pretty woman<br/>Yeah yeah yeah yeah<br/>O yalmipgedo yeojeonhi neon joha boyeo pretty woman<br/>Oh pretty woman<br/><br/>Don't wanna be fool wanna be cool<br/>Wanna be loved neowaui same love<br/>I know it's over<br/>Don't wanna be fool wanna be cool<br/>Wanna be loved neowaui same love<br/>Baby I want it<br/><br/>Neo yojeume eotteoke jinaego inna<br/>Gunggeumhae boni johayoga bitna<br/>Na eobsi jal saneun niga<br/>Wae saenggangnatji<br/>Chajaon geon hansimman deo<br/>Nado nureugo galge ni geul wie<br/>Nan yojeum neo eobsi ireoke jinae<br/>Know you want it<br/><br/>Neon nami doego ohiryeo deo joha boyeo pretty woman<br/>Yeah yeah yeah yeah<br/>O yalmipgedo yeojeonhi neon joha boyeo pretty woman<br/>Oh pretty woman<br/><br/>Don't wanna be fool wanna be cool<br/>Wanna be loved neowaui same love<br/>I know it's over<br/>Don't wanna be fool wanna be cool<br/>Wanna be loved neowaui same love<br/>Baby I want it<br/>"
		},
		{
			"id": 13,
			"name_category": "ENHYPEN BEST SONG",
			"title": "Just A Little Bit",
			"image": "file:///android_asset/image/anyar.jpg",
			"link_mp3": "mp3/JustALittleBit.mp3",
			"duration": "222",
			"lyrics": "<br/>Nae son wie noin deusi<br/>Nae ujureul tongjehaetji<br/>Saramdeurui maeumkkaji<br/>Da ppeonhae boyeotji yeah<br/>Jinsim eomneun misomyeon modu swiwotdeon<br/>Nae jageun sesang wi<br/>Neoran gyunyeori<br/><br/>Neon waenji mwonga dalla<br/>Jakkuman nareul heundeureo<br/>Neoui nunbit maltu style<br/>Oh machi dareun sesange saneun deuthae<br/>Baby meoriwaneun sanggwaneopsi<br/>Gaseumi neol wonhage hae<br/>Neol mannan ihu<br/><br/>Just a little bit, just a little bit<br/>Singyeong sseuyeo neoran jonjaega<br/>Just a little bit, just a little bit<br/>Nae segyereul muneotteuryeo<br/>Nae ujuui kkaejin teumeuro<br/>Georeowa nuneul matchugo<br/>Amureochi anke mareul geoneun neo mollasseo<br/>Just a little bit just a little bit<br/>Ireoke doelji<br/><br/>Chinjeolhage jeokin seolmyeongseocheoreom (Everything)<br/>Kkumin miso dwie sumgin nae mameul ilgeo (Always know)<br/>Itorok muhaehan eolgullo<br/>Nal wiheomhage haneun neo<br/>Jakku niga gunggeumhaejyeo<br/>Meomchul su eopseo<br/><br/>Just a little bit, just a little bit<br/>Singyeong sseuyeo neoran jonjaega<br/>Just a little bit, just a little bit<br/>Nae segyereul muneotteuryeo<br/>Nae ujuui kkaejin teumeuro<br/>Georeowa nuneul matchugo<br/>Amureochi anke mareul geoneun neo<br/>Mollasseo<br/><br/>Kkoigo eongkin bokjapan mami<br/>Natseoljiman wae silchiga aneunji<br/>Eodinga bulpyeonhan geureomyeonseo dalkomhan<br/>Cheoeum neukkineun gamjeonge ppajin geot gata<br/><br/>Just a little bit, just a little bit<br/>Segyega muneojyeo naeryeo<br/>Just a little bit, just a little bit<br/>Neoui jungnyeoge kkeullyeoga<br/>Nae ujuneun sarajyeogago<br/>Hanassik neoro chaewojyeo<br/>Sesang modeun geol anda mideonneunde<br/><br/>Mollasseo (Just a little bit, just a little bit)<br/>Hmm mollasseo (Just a little bit, just a little bit)<br/>Yeah"
		},
		{
			"id": 14,
			"name_category": "ENHYPEN BEST SONG",
			"title": "Let Me In",
			"image": "file:///android_asset/image/anyar.jpg",
			"link_mp3": "mp3/LetMeIn.mp3",
			"duration": "199",
			"lyrics": "<br/>I'll be your boyfriend<br/>(I'll be your boyfriend)<br/>Yeah baby let's go<br/><br/>Deureogago sipeo neoui kyubeu sogeuro<br/>Yeah yeah yeah yeah<br/>Tumyeonghage bichyeo pureun mulgyeol sairo<br/>Yeah yeah yeah yeah<br/>Oh boseokcheoreom bichi naneun neo neo neo<br/>Geugoseun neoui jageun castleya<br/>Deureogago sipeo neoui segye sogeuro<br/><br/>Ipgimeul bureobwa<br/>Geu wiro geuryeobwa<br/>Nae mameul arabwa<br/>Dallago malharago<br/>Nal geugose heorakaejwo<br/><br/>Urin machi like a moonlight<br/>Hamkkeramyeon have a good time<br/>Nae mami neol like<br/>Yeah yeah yeah yeah yeah yeah yeah<br/>Yeah yeah yeah yeah yeah yeah yeah<br/><br/>Yeoreojullae neoui window<br/>Chaja hemaen naui Nemo<br/>Nae mami neol like<br/>Yeah yeah yeah yeah yeah yeah yeah<br/>Yeah yeah yeah yeah yeah yeah yeah<br/>I'll be your boyfriend<br/><br/>I'll give you my lo lo lo love<br/>I'll give you my love<br/>I'll be your boyfriend<br/><br/>I'll give you my blo blo blo blood<br/>I'll give you my blood<br/>I'll be your boy boyfriend<br/><br/>Ooh ah<br/>Radi ra ra ra<br/>Ooh ah<br/>Bring it back<br/><br/>Eojjeom naega neoreul dachige halji molla<br/>Yeah yeah yeah yeah<br/>Neoui wanbyeokameul kkaetteuriljido molla<br/><br/>Jobeun neoui segyen<br/>Honjado wanbyeokae<br/>Hajiman milchyeonaeji marajwo badajwo<br/>Nal geugose heorakaejwo<br/><br/>Urin machi like a moonlight<br/>Hamkkeramyeon have a good time<br/>Nae mami neol like<br/>Yeah yeah yeah yeah yeah yeah yeah<br/>Yeah yeah yeah yeah yeah yeah yeah<br/><br/>Yeoreojullae neoui window<br/>Chaja hemaen naui Nemo<br/>Nae mami neol like<br/>Yeah yeah yeah yeah yeah yeah yeah<br/>Yeah yeah yeah yeah yeah yeah yeah<br/>I'll be your boyfriend<br/><br/>Oh shining bluega bulgeojyeodo<br/>(Bulgeojyeodo bulgeojyeodo)<br/>Baby apeum soge gippeumi pieona<br/>Woo yeah<br/>Urin machi like a moonlight<br/>Hamkkeramyeon have a good time<br/>Nae mami neol like<br/>Yeah yeah yeah yeah yeah yeah yeah<br/>Yeah yeah yeah yeah yeah yeah yeah<br/><br/>Yeoreojullae neoui window<br/>Chaja hemaen naui Nemo<br/>Nae mami neol like<br/>Yeah yeah yeah yeah yeah yeah yeah<br/>Yeah yeah yeah yeah yeah yeah yeah<br/>I'll be your boyfriend<br/><br/>I'll give you my lo lo lo love<br/>I'll give you my love<br/>I'll be your boyfriend<br/><br/>I'll give you my blo blo blo blood<br/>I'll give you my blood<br/>I'll be your boy boyfriend<br/><br/>I can be the one for you for good<br/>I can be the one for you for good<br/>I'll be your boyfriend<br/>I can be the one for you for good, baby<br/>I'll be your boy boyfriend<br/>"
		},
		{
			"id": 15,
			"name_category": "ENHYPEN BEST SONG",
			"title": "Let Me In_Japanese Version",
			"image": "file:///android_asset/image/anyar.jpg",
			"link_mp3": "mp3/LetMeIn_JapaneseVersion.mp3",
			"duration": "254",
			"lyrics": "<br/>I'll be your boyfriend<br/>(I'll be your boyfriend)<br/>Yeah baby let's go<br/><br/>Hairitai yo sonoCubeno naka<br/>Yeah yeah yeah yeah<br/>Sukitōru yo ao no namima ni<br/>Yeah yeah yeah yeah<br/>Oh mabushiku kagayaku nonono<br/>Kimi no chīsanacastlesa<br/>Hairitai yo kimi no sekai ni<br/><br/>Iki o kakete<br/>Kaite mite<br/>Omoi o shitte<br/>Hoshī to itte<br/>Soko e yurushite yo<br/><br/>Futari wa like a moonlight<br/>Isshonara have a good time<br/>Kokoro ga like<br/>Yeah yeah yeah yeah yeah yeah yeah<br/>Yeah yeah yeah yeah yeah yeah yeah<br/><br/>Aite sono window<br/>Sagasu boku no Nemo<br/>Kokoro ga like<br/>Yeah yeah yeah yeah yeah yeah yeah<br/>Yeah yeah yeah yeah yeah yeah yeah<br/>I'll be your boyfriend<br/><br/>I'll give you my lo lo lo love<br/>I'll give you my love<br/>I'll be your boyfriend<br/>I'll give you my blo blo blo blood<br/>I'll give you my blood<br/>I'll be your boy boyfriend<br/><br/>Ooh ah<br/>Radi ra ra ra<br/>Ooh ah<br/>Bring it back<br/><br/>Kimi o kizutsukeru kamo shirenai<br/>Yeah yeah yeah yeah<br/>Sono muketsu-sa kowareru kamo na<br/><br/>Kimi no sekai wa<br/>Sudeni kanpekide<br/>Demo tsukihanasanaide okure<br/>Soko e yurushite yo<br/><br/>Futari wa like a moonlight<br/>Isshonara have a good time<br/>Kokoro ga like<br/>Yeah yeah yeah yeah yeah yeah yeah<br/>Yeah yeah yeah yeah yeah yeah yeah<br/><br/>Aite sono window<br/>Sagasu boku no Nemo<br/>Kokoro ga like<br/>Yeah yeah yeah yeah yeah yeah yeah<br/>Yeah yeah yeah yeah yeah yeah yeah<br/>I'll be your boyfriend<br/><br/>Oh shining blue ga akakute<br/>(Akakute akakute)<br/>Baby itami ni hanagasaku<br/>Woo yeah<br/><br/>Futari wa like a moonlight<br/>Isshonara have a good time<br/>Kokoro ga like<br/>Yeah yeah yeah yeah yeah yeah yeah<br/>Yeah yeah yeah yeah yeah yeah yeah<br/><br/>Aite sono window<br/>Sagasu boku no Nemo<br/>Kokoro ga like<br/>Yeah yeah yeah yeah yeah yeah yeah<br/>Yeah yeah yeah yeah yeah yeah yeah<br/>I'll be your boyfriend<br/><br/>I'll give you my lo lo lo love<br/>I'll give you my love<br/>I'll be your boyfriend<br/>I'll give you my blo blo blo blood<br/>I'll give you my blood<br/>I'll be your boy boyfriend<br/><br/>I can be the one for you for good<br/>I can be the one for you for good<br/>I'll be your boyfriend<br/>I can be the one for you for good, baby<br/>I'll be your boy boyfriend<br/>"
		},
		{
			"id": 16,
			"name_category": "ENHYPEN BEST SONG",
			"title": "Love Me right",
			"image": "file:///android_asset/image/anyar.jpg",
			"link_mp3": "mp3/LoveMeright.mp3",
			"duration": "212",
			"lyrics": "<br/>Oh Yeah! C'mon!<br/><br/>Take your time<br/>Waenji dugeundaeneun bamiya<br/>Na Na Na Na<br/>Na Na Na Na<br/><br/>So tonight<br/>Dal kkeutkkaji dallyeogabolkka<br/>Yea Yea Yea Yea<br/>Yea Yea Yea Yea<br/><br/>Just right<br/>Sidongeul georeo eksere bareul ollyeo<br/>Modeun geosi teukbyeolhae<br/>Neowaneun jal eoullyeo<br/>Mueoseul wonhadeon Imma make it work (Yeah)<br/><br/>Shawty, Imma party till the sun down<br/>Jigeum i sinbiroun neukkimeun mwolkka<br/>Wajwo naegero eoseo before the sun rise<br/>Nega eopsneun nan eodil gado Nobody (Yeah) o!<br/><br/>Doro wie yeogin runway<br/>Nal baraboneun nun sok milky way<br/>Just love me right (aha!)<br/>Baby love me right (aha!)<br/>O! naegero wa mangseorijima<br/>Neon maehokjeogin naui universe<br/>Just love me right (aha!)<br/>Nae ujuneun jeonbu neoya<br/><br/>Just love me right<br/>Just love me right<br/>Just love me right<br/>Nae ujuneun jeonbu neoya<br/><br/>Shine a light byeolbit sogeul dallyeo<br/>Eunhasul geonneo<br/>Na Na Na Na<br/>Na Na Na Na<br/>Meomchul sun eopseo oye!<br/><br/>Uril bichuneun dalbicceun yeojeonhaji<br/>Ne gwedo an hemaego isseo nan ajik<br/>I can do thit all night long baby<br/>Nega eopsneun nan eodil gado banjjokjjarinikka<br/>Ou!<br/><br/>Dalbit chanranhan bam pyeolchyeojin<br/>Byeoldeurui bulkkoccnori<br/>Jom deo nopi naragabolkka (naragabolkka)<br/><br/>Gaseum teojildeushan i sungan<br/>Uri dulman tteoolla<br/>Bal mite jigureul dugo love me right<br/><br/>Doro wie yeogin runway<br/>Nal baraboneun nun sok milky way<br/>Just love me right (aha!)<br/>Baby love me right (aha!)<br/>So come on baby nuni busige<br/>Deo areumdaun neoui universe (areumdaun lady)<br/>Just love me right (aha!)<br/>Nae ujuneun jeonbu neoya (o!)<br/><br/>Just love me right<br/>Just love me right (Can you love me right)<br/>Just love me right<br/>I just wanna make you love me<br/>(Nae ujuneun jeonbu neoya)<br/><br/>Su eopsneun bami chajawado<br/>Nae haneuren ojik neoman bitna (Woo Yeah)<br/>Soksagyeojwo naegeman<br/>Bamhaneureul neowa naega<br/>Muldeuryeoga<br/><br/>Doro wie yeogin runway<br/>Nal baraboneun nun sok milky way<br/>Just love me right (aha!)<br/>Baby love me right (aha!)<br/>O! naegero wa mangseorijima<br/>Neon maehokjeogin naui universe<br/>Just love me right (aha!)<br/>Nae ujuneun jeonbu neoya (nae ujuneun jeonbu neoya)<br/><br/>Just love me right (Oh oh oh yeah)<br/>Just love me right<br/>Just love me right (urimanui sigan)<br/>Nae ujuneun jeonbu neoya<br/>Just love me right<br/>Just love me right<br/>Just love me right<br/>(Jjarishan Cosmic ride, urimanui yaganbihaeng)<br/>I just wanna make you love me<br/><br/>Yea (Woo You got to love)<br/>Yea (You got to love me)<br/>Yea<br/>Nae ujuneun jeonbu neoya (nae ujuneun jeonbu neoya)<br/>Yea (You love me)<br/>Yea (You love me)<br/>Yea<br/>Nae ujuneun jeonbu neoya<br/>"
		},
		{
			"id": 17,
			"name_category": "ENHYPEN BEST SONG",
			"title": "Mixed Up",
			"image": "file:///android_asset/image/anyar.jpg",
			"link_mp3": "mp3/MixedUp.mp3",
			"duration": "210",
			"lyrics": "<br/>Nal gaman mot duji<br/>Mak sikkeureopge ullin allimeum<br/>Goyohagil baran sesangi<br/>All day long, all day long<br/>Yodongchyeo dasi (yodongchyeo dasi)<br/><br/>Jageukjeogin gasip juingongi dwae nan<br/>I don't understand, don't understand<br/>Tteugeowo bulbuteun diem jigyeowo ireon yumyeongse<br/>Ijeojwo joyonghage (Oh)<br/><br/>Geunde ige da mwoya<br/>Mari dwae mariya nal hyanghan galjeungdeul<br/>Mundeuk nuneul tteoboni<br/>Hwajeui jungsim (Hoo, ha)<br/><br/>Mixed up sijakdwaesseo tto<br/>Sesangi byeorangan dwijipyeosseo balkak<br/>Mixed up jyaega gyaenyago<br/>Nae yaegiman hae da geurae narago<br/>Nado moreuge juingongi doen<br/>Gasip gasip (Oh)<br/>Mixed up nal naebeoryeo dwo<br/>Haru jongil mixed up, mixed up, oh, oh<br/><br/>Hanbatang tto morachyeo sikkeureoun taepung sok<br/>Na honjaman goyohal ppun<br/>Uimi eomneun daneoe buri buteo beonjyeoga<br/>Geotjabeul su eopseojyeo (eopseo deo)<br/><br/>Nae mamdaero andwae imi out of control<br/>I don't understand, don't understand<br/>Gamanhi isseodo naege jilmuni ieojyeo machi<br/>Kkeuchiran eopseo boyeo<br/><br/>Hanjjogeuroman doldeon<br/>Ilsangeun eopseo byeorangan dwijipyeo (modeun ge dwijipyeo)<br/>Gyeonggyereul chimbeomhaewatji<br/>Eojjeomyeon destiny (I won't stop)<br/><br/>Mixed up sijakdwaesseo tto<br/>Sesangi byeorangan dwijipyeosseo balkak<br/>Mixed up jyaega gyaenyago<br/>Nae yaegiman hae da geurae narago<br/>Nado moreuge juingongi doen<br/>Gasip gasip (Oh)<br/>Mixed up nal naebeoryeo dwo<br/>Haru jongil mixed up, mixed up, oh, oh<br/><br/>Eojireo eojireowo<br/>Sumgyeodo sikkeureo sikkeureowo (amuri sumeodo)<br/>Eonjena hwajeui jungsime seo inneun na<br/>Byeorangan i sesang gajang teukbyeolhan ingan (summan swieodo nan)<br/>Eojireo eojireowo<br/>Gamchwodo sikkeureo sikkeureowo (jeonbu da nae tasiya)<br/>Dasi tto hwajeui jungsime seo inneun na<br/>Geurae nan i sesang gajang teukbyeolhan ingan<br/><br/>Mixed up jeulgyeobolge tto<br/>Sesangeul byeorangan dwijibeonwa balkak<br/>Mixed up jyaega gyaenyago<br/>Boyeojulge jal bwa ige narago<br/>Nado moreuge juingongi doen<br/>Gasip gasip<br/>Mixed up nal naebeoryeo dwo<br/>Haru jongil mixed up, mixed up, oh, oh<br/>"
		},
		{
			"id": 18,
			"name_category": "ENHYPEN BEST SONG",
			"title": "Not For Sale",
			"image": "file:///android_asset/image/anyar.jpg",
			"link_mp3": "mp3/NotForSale.mp3",
			"duration": "208",
			"lyrics": "<br/>Cheoeum neukkineun feeling<br/>Neol mannago jakkuman simjangi isanghae, isanghae<br/>Silchineun aneun feeling<br/>Neol mannagoseo dallajin moseubi nan eosaekae, oh, baby<br/><br/>Plasticeuro mandeun sesangen<br/>Gagyeokpyoro gadeukae<br/>Ireul jwoya ireul banneun ge<br/>Yeogiseoneun dangyeonhae<br/>Simjangeun for sale (Ooh)<br/>Sarangdo for sale<br/><br/>Idaero manghaebeoril sesang<br/>Gidae hana eopdeon naege<br/>Semeuron guhal su eomneun<br/>Dapdeureul gareuchyeojun neo<br/>Chagaun simjang wiui price tag<br/>Natseon ongiro tteeonaen<br/>Neoraneun jonjaeneun naege isseo<br/>You're not, you're not for sale<br/><br/>You're not for sale, woah-oh-oh<br/>Pal su eomne (Ooh-ooh)<br/>Sal su eomne, yeah, yeah, ooh<br/><br/>Cheoeum neukkineun feeling<br/>Neol mannago jakkuman simjangi isanghae, isanghae<br/>Silchineun aneun feeling<br/>Neol mannagoseo dallajin moseubi nan eosaekae, oh, baby<br/><br/>Geoseulleo juji anado dwae<br/>Jeonbu jugo sipeun geol<br/>Amuraedo manghae beorin geon<br/>Nain geonman gateungeol<br/>Geuraedo jote<br/>Simjangi malhae<br/><br/>Idaero manghaebeoril sesang<br/>Gidae hana eopdeon naege<br/>Semeuron guhal su eomneun<br/>Dapdeureul gareuchyeojun neo<br/>Chagaun simjang wiui price tag<br/>Natseon ongiro tteeonaen<br/>Neoraneun jonjaeneun naege isseo<br/>You're not, you're not for sale<br/><br/>You're not for sale, woah-oh-oh<br/>Pal su eomne<br/>Sal su eomne, yeah, yeah, ooh<br/>"
		},
		{
			"id": 19,
			"name_category": "ENHYPEN BEST SONG",
			"title": "Permission To Dance",
			"image": "file:///android_asset/image/anyar.jpg",
			"link_mp3": "mp3/PermissionToDance.mp3",
			"duration": "238",
			"lyrics": "<br/>It's the thought of being young<br/>When your heart's just like a drum<br/>Beating louder with no way to guard it<br/>When it all seems like it's wrong<br/>Just sing along to Elton John<br/>And to that feeling, we're just getting started<br/><br/>When the nights get colder<br/>And the rhythms got you falling behind<br/>Just dream about that moment<br/>When you look yourself right in the eye, eye, eye<br/>Then you say<br/><br/>I wanna dance<br/>The music's got me going<br/>Ain't nothing that can stop how we move, yeah<br/>Let's break our plans<br/>And live just like we're golden<br/>And roll in like we're dancing fools<br/><br/>We don't need to worry<br/>'Cause when we fall, we know how to land<br/>Don't need to talk the talk<br/>Just walk the walk tonight<br/>'Cause we don't need Permission to Dance<br/><br/>There's always something that's standing in the way<br/>But if you don't let it faze ya<br/>You'll know just how to break<br/>Just keep the right vibe, yeah<br/>'Cause there's no looking back<br/>There ain't no one to prove<br/>We don't got this on lock, yeah<br/><br/>The wait is over<br/>The time is now<br/>So let's do it right<br/>Yeah, we'll keep going<br/>And stay up until we see the sunrise<br/>And we'll say<br/><br/>I wanna dance<br/>The music's got me going<br/>Ain't nothing that can stop how we move, yeah<br/>Let's break our plans<br/>And live just like we're golden<br/>And roll in like we're dancing fools<br/><br/>We don't need to worry<br/>'Cause when we fall, we know how to land<br/>Don't need to talk the talk<br/>Just walk the walk tonight<br/>'Cause we don't need Permission to Dance<br/><br/>Da-na-na-na-na-na-na<br/>Da-na-na-na-na-na-na<br/>Da-na-na-na-na-na-na<br/>No, we don't need Permission to Dance<br/><br/>Da-na-na-na-na-na-na<br/>Da-na-na-na-na-na-na<br/>Da-na-na-na-na-na-na<br/><br/>Well, let me show ya<br/>That we can keep the fire alive<br/>'Cause it's not over<br/>'Till it's over, say it one more time<br/>Say<br/><br/>I wanna dance<br/>The music's got me going<br/>Ain't nothing that can stop how we move, yeah<br/>Let's break our plans<br/>And live just like we're golden<br/>And roll in like we're dancing fools<br/><br/>We don't need to worry<br/>'Cause when we fall, we know how to land<br/>Don't need to talk the talk<br/>Just walk the walk tonight<br/>'Cause we don't need Permission to Dance<br/>"
		},
		{
			"id": 20,
			"name_category": "ENHYPEN BEST SONG",
			"title": "Billy Poco",
			"image": "file:///android_asset/image/anyar.jpg",
			"link_mp3": "mp3/BillyPoco.mp3",
			"duration": "247",
			"lyrics": "<br/>Billibillipoko billipoko yeah<br/>Billibillipoko billipoko maekseu keuriseu<br/>Billibillipoko billipoko yeah<br/>Billibillipoko billipoko maekseu keuriseu<br/><br/>Hebihebi one!<br/>My name is billi<br/>Naege malman hae<br/>Da mireo julge<br/><br/>Neolbeun baetopan teunteunhan bakwi<br/>Billi billi - himsen chingu billi<br/><br/>Hebihebi two!<br/>My name is poko<br/>Naege malman hae<br/>Da jeongni halge<br/><br/>Eotteon jangaemuldo duryeopji ana<br/>Poko poko - meotjin chingu poko<br/>Oh Oh Oh Oh Oh<br/>Uriman mideo<br/>Oh Oh Oh Oh Oh<br/>Eogieocha!<br/>Oh Oh Oh Oh Oh<br/><br/>Himi himi sosa oh<br/>Nopi nopi sosa hey!<br/><br/>Billibillipoko billipoko yeah<br/>Billibillipoko billipoko maekseu keuriseu<br/>Billibillipoko billipoko yeah<br/>Billibillipoko billipoko maekseu keuriseu<br/><br/>Hebihebi three!<br/>My name is maekseu<br/>Naege malman hae<br/>Da deureo julge<br/><br/>Sesang geu mueotdo mugeopji ana<br/>Maekseu maekseu - deumjikan cha maekseu<br/><br/>Hebihebi four!<br/>My name is keuriseu<br/>Neol jikyeo julge<br/><br/>Eotteon eoryeoumdo igil su isseo<br/>Keuriseu keuriseu - meotjin chingu keuriseu<br/>Oh Oh Oh Oh Oh<br/>Uriman mideo<br/>Oh Oh Oh Oh Oh<br/>Eogieocha!<br/>Oh Oh Oh Oh Oh<br/><br/>Himi himi sosa oh<br/>Nopi nopi sosa hey!<br/>I'm heavy~!<br/>(We) Heavy heavy!<br/>I'm heavy~!<br/>(We) Heavy heavy!<br/><br/>Billibillipoko billipoko yeah<br/>Billibillipoko billipoko maekseu keuriseu<br/>Billibillipoko billipoko yeah<br/>Billibillipoko billipoko maekseu keuriseu<br/>"
		},
		{
			"id": 21,
			"name_category": "ENHYPEN BEST SONG",
			"title": "Boy In Luv",
			"image": "file:///android_asset/image/anyar.jpg",
			"link_mp3": "mp3/BoyInLuv.mp3",
			"duration": "246",
			"lyrics": "<br/>Doegopa neoui oppa<br/>Neoui sarangi nan neomu gopa<br/>Doegopa neoui oppa<br/>Neol gatgo mal geoya dugo bwa<br/><br/>Wae nae mameul heundeuneun geonde<br/>Wae nae mameul heundeuneun geonde<br/>Wae nae mameul heundeuneun geonde<br/>Heundeuneun geonde heundeuneun geonde<br/><br/>Appa, appan daeche eoddeohge<br/>Eommahante gobaekhan geonji<br/>Pyeonjirado sseoya doelleonji<br/>Mwonji, ni apeseo nan meonji<br/><br/>Gwaenhi tiktikdaego<br/>Ssikssikdaego jingjingdaege dwae<br/>Naneun jinjihande<br/>Jjijilhage sibina geolge dwae<br/>Mwonde singyeong sseuyeo<br/>Da keun nal aero mandeureo<br/>Geokkuro dwijibeulkkyeo<br/>Inyeoneul yeonineuro<br/><br/>Daehakggajido neorang gandamyeon<br/>Cham jal gal geot gata<br/>Ganadaramabasaa hakunamatata!<br/>Ddokgateun peuropil sajin<br/>Wae jakku hwaginhalkka<br/>Geureohdago chakgakhajima<br/>Swiun namja anya<br/><br/>Andal nasseo na andal nasseo<br/>Niga mwonde?<br/>Neoman jallasseo?<br/>Wae nareul jakku nollyeo nollyeo<br/>Neo ije geuman hol' up hol' up<br/><br/>Ggwak jaba nal deopchigi jeone<br/>Nae mami neol nohchigi jeone<br/>Say what you want<br/>Say what you want<br/>Niga jinjjaro wonhaneun ge mwoya<br/><br/>Ggwak jaba nal deopchigi jeone<br/>Nae mami neol nohchigi jeone<br/>Say what you want<br/>Say what you want<br/>Niga jinjjaro wonhaneun ge mwoya<br/><br/>Wae nae mameul heundeuneun geonde<br/>Wae nae mameul heundeuneun geonde<br/>Wae nae mameul heundeuneun geonde<br/>Heundeuneun geonde heundeuneun geonde<br/><br/>Geoteuron bad bad girl,<br/>Sogeun deo bad bad girl<br/>Na gateun namjal nohchimyeon<br/>Huhoehage doel geol<br/>Mesinjeo hwaginhaenohgo<br/>Nureuji anhneun neoui haengwi<br/>Il jari eobseo jimgwa dongsie sokman<br/>Taji nebigeisyeonina salkka bwa<br/>(Ppareum ppareum ppareum) eopilharyeogo<br/>Gyesok nan (adung badung badung)<br/>Jinsim? (I got 'em) dwissim? (I got 'em)<br/>Naega yuilhage gajji mothan geon<br/>Neoui (areum areum daum)<br/><br/>I naega eoddeohge<br/>Byeonhamyeon doegetni, hol' up<br/>Mildang? eojang?<br/>Geureon geo nan jal molleo<br/>Daesin apeumyeon<br/>Irilgu malgo nal bulleo<br/>Niga ullamyeon ureo<br/>Useuramyeon useo, gureuramyeon gulleo<br/><br/>Andal nasseo na andal nasseo<br/>Niga mwonde?<br/>Neoman jallasseo?<br/>Wae nareul jakku nollyeo nollyeo<br/>Neo ije geuman hol' up hol' up<br/><br/>Ggwak jaba nal deopchigi jeone<br/>Nae mami neol nohchigi jeone<br/>Say what you want<br/>Say what you want<br/>Niga jinjjaro wonhaneun ge mwoya<br/><br/>Ggwak jaba nal deopchigi jeone<br/>Nae mami neol nohchigi jeone<br/>Say what you want<br/>Say what you want<br/>Niga jinjjaro wonhaneun ge mwoya<br/><br/>Doegopa neoui oppa<br/>Neoreul hyanghan naui maeumeul wae molla<br/>Nareul moreun cheokhaedo chagaun cheokhaedo<br/>Neol mireonaejin mothagesseo<br/>Doegopa neoui oppa<br/>Neoui namjaga doel geoya dugo bwa<br/>Naui maeumi nege datorok<br/>Jigeum dallyeogal geoya<br/><br/>Ggwak jaba nal deopchigi jeone<br/>Nae mami neol nohchigi jeone (nohchigi jeone)<br/>Say what you want<br/>Say what you want<br/>Niga jinjjaro wonhaneun ge mwoya<br/><br/>Ggwak jaba nal deopchigi jeone<br/>Nae mami neol nohchigi jeone<br/>Say what you want<br/>Say what you want<br/>Niga jinjjaro wonhaneun ge mwoya<br/>"
		},
		{
			"id": 22,
			"name_category": "ENHYPEN BEST SONG",
			"title": "Go Big or Go Home",
			"image": "file:///android_asset/image/anyar.jpg",
			"link_mp3": "mp3/GoBigorGoHome.mp3",
			"duration": "185",
			"lyrics": "<br/>Don't get away, don't get away<br/>I gotta make I'm the one<br/>Mo animyeon do animyeon mo animyeon dorago<br/>I need a diamond ring<br/>Momani naui gil<br/>Nan rujeoga anin wineoga dwae that's my way<br/>Go big or go Home<br/><br/>Seungni anim paebaeppunin game gateun sesang<br/>Ganeun geoya right right now<br/>Doellomdoereul mideo eochapi doel nom doenikka<br/>I han panui fight right now<br/><br/>Let's go, go, go<br/>Nae apen eonjena mo, mo, mo<br/>Junggan gateun geon feels like a loss<br/>Gominhal sigane<br/>Gachyareul ppobaboja<br/>Go big or go Home<br/><br/>I'm feeling lucky yegami jochi<br/>Dugeungeorime feels alright<br/>Nae unmyeongeun daebak<br/>Ireon geunjagam<br/>All anim nothing jilleobwa<br/><br/>We going going going we ride<br/>I'm feeling feeling feeling alright<br/>We going going going we ride we ride<br/>Go big or go Home<br/><br/>Don't get away, don't get away<br/>I gotta make I'm the one<br/>Mo animyeon do animyeon mo animyeon dorago<br/>I need a diamond ring<br/>Momani naui gil<br/>Nan rujeoga anin wineoga dwae that's my way<br/>Go big or go Home<br/><br/>Geobuhal su eomneun russian roulette gateun sal<br/>Eojjaetgeona I'll survive<br/>Aitem hoekdeuk hapseong ganghwa I can make it right<br/>Jasin itge choose right now<br/><br/>Let's go, go, go<br/>Nae apen eonjena mo, mo, mo<br/>Junggan gateun geon feels like a loss<br/>Gominhal sigane<br/>Gachyareul ppobaboja<br/>Go big or go Home<br/><br/>I'm feeling lucky yegami jochi<br/>Dugeungeorime feels alright<br/>Nae unmyeongeun daebak<br/>Ireon geunjagam<br/>All anim nothing jilleobwa<br/><br/>We going going going we ride<br/>I'm feeling feeling feeling alright<br/>We going going going we ride we ride<br/>Go big or go Home<br/><br/>Don't get away, don't get away<br/>I gotta make I'm the one<br/>Mo animyeon do animyeon mo animyeon dorago<br/>I need a diamond ring<br/>Momani naui gil<br/>Nan rujeoga anin wineoga dwae that's my way<br/>Go big or go Home<br/>"
		},
		{
			"id": 23,
			"name_category": "ENHYPEN BEST SONG",
			"title": "Polaroid Love",
			"image": "file:///android_asset/image/anyar.jpg",
			"link_mp3": "mp3/PolaroidLove.mp3",
			"duration": "234",
			"lyrics": "<br/>It's like a polaroid love<br/>Sarang, chonseureon geu gamjeong<br/>Geunde nae gaseumi ttwieo<br/>Wae na irae na<br/><br/>Wae sarange mongmaeneun geonji<br/>Eochapi ppeonhan gamjeongijana<br/>Bunmyeong da anda mideotji<br/>Algodo ppajin hamjeonginga bwa<br/><br/>Nado moreuge When you call my name<br/>Gaseum apeuge naui simjangi kungkung<br/><br/>It's like a polaroid love<br/>Sarang, chonseureon geu gamjeong<br/>Geunde nae gaseumi ttwieo<br/>Wae na irae na<br/>It's like a polaroid love<br/>Nae tteutdaero doeji ana<br/>Heunhan filterjocha eopseo<br/>But I love that vibe<br/>(Yeah yeah yeah yeah)<br/><br/>Neol hyanghan nae mameul yeogi<br/>Bojeong eopsi saegineun geoya<br/>Jeomjeom ttoryeothaejyeo gaji<br/>I mameun sesang dan han jang ppuniya<br/><br/>Nado moreuge When you call my name<br/>Gaseum apeuge naui simjangi kungkung<br/><br/>It's like a polaroid love<br/>Sarang, chonseureon geu gamjeong<br/>Geunde nae gaseumi ttwieo<br/>Wae na irae na<br/><br/>It's like a polaroid love<br/>Nae tteutdaero doeji ana<br/>Heunhan filterjocha eopseo<br/>But I love that vibe<br/>(Yeah yeah yeah yeah)<br/><br/>Polaroid Love<br/>Chonseureon geu gamjeong<br/>Polaroid Love<br/>I love that vibe<br/><br/>Nado moreuge When you call my name<br/>Gaseum apeuge naui simjangi kungkung<br/><br/>It's like a polaroid love<br/>Sarang, chonseureon geu gamjeong<br/>Geunde nae gaseumi ttwieo<br/>Wae na irae na<br/><br/>It's like a polaroid love<br/>Nae tteutdaero doeji ana<br/>Heunhan filterjocha eopseo<br/>But I love that vibe<br/>(Yeah yeah yeah yeah)<br/>"
		},
		{
			"id": 24,
			"name_category": "ENHYPEN BEST SONG",
			"title": "Tamed Dashed",
			"image": "file:///android_asset/image/anyar.jpg",
			"link_mp3": "mp3/TamedDashed.mp3",
			"duration": "274",
			"lyrics": "<br/>Gildeullyeojimyeon doena<br/>Nal maeryohan yongmangui geu seomgwang<br/>Kkumeun areumdapge tto chuhage<br/>Moseubeul bakkwo mak<br/>Oh, eolkigo seolkyeojin<br/>Chawon soge seontaegui dillema<br/>Bareul naeditgiga nan geobi na<br/>I hate to be or not<br/><br/>Like hot summer (Na, na, na)<br/>Ildan ttwieo (Na, na, na)<br/>Bulkkoche sarojapyeodo beoryeojindaedo<br/>Jeongdabeun jigeum al su eopseo<br/><br/>Tteugeoun simjang nareul deryeoga<br/>Mongmareun galjeung I can't stop me like<br/>Summer (Na, na, na)<br/>Ildan ttwieo (Na, na, na)<br/>Bultaneun taeyang nal ikkeureoga<br/>Naui nachimban please don't leave me now<br/>Summer (Na, na, na)<br/>Geunyang ttwieo (Na, na, na)<br/><br/>Ooh-ooh-ooh, ooh-ooh-ooh, ooh-ooh-ooh<br/>Ooh-ooh-ooh, ooh-ooh<br/>Jeongdabi anira haedo<br/>Ooh-ooh-ooh, ooh-ooh<br/>Jeongdabi anira haedo<br/><br/>Oh, meomchwoyaman hana<br/>Takan siya kkume jungdokdoen na<br/>Oh, geuriun eorin nal<br/>Iksukan na boijiga ana<br/><br/>Like hot summer (Na, na, na)<br/>Ildan ttwieo (Na, na, na)<br/>Idaero dallinda haedo meomchunda haedo<br/>Gyeolgwaneun jigeum al su eopseo<br/><br/>Tteugeoun simjang nareul deryeoga<br/>Mongmareun galjeung I can't stop me like<br/>Summer (Na, na, na)<br/>Ildan ttwieo (Na, na, na)<br/>Bultaneun taeyang nal ikkeureoga<br/>Naui nachimban please don't leave me now<br/>Summer (Na, na, na)<br/>Geunyang ttwieo (Na, na, na)<br/><br/>Jigeutjigeuthan gomin<br/>Ppulgwa ppul saieseo<br/>So keep it going, keep it going on right now<br/>Just keep it running, keep it running up right now<br/>Nawa gateun gomine gatyeoinneun neo<br/>Eotteoke haeya halji mollaseo meomchwo inneun neo<br/>Geureol ttaen nae soneul japgo dallyeobwa<br/><br/>Tteugeoun simjang nareul deryeoga<br/>Mongmareun galjeung I can't stop me like<br/>Summer (Na, na, na)<br/>Ildan ttwieo (Na, na, na)<br/>Bultaneun taeyang nal ikkeureoga<br/>Naui nachimban please don't leave me now<br/>Summer (Na, na, na)<br/>Geunyang ttwieo (Na, na, na)<br/><br/>Ooh-ooh-ooh, ooh-ooh-ooh, ooh-ooh-ooh<br/>Ooh-ooh-ooh, ooh-ooh<br/>Jeongdabi anira haedo<br/>Ooh-ooh-ooh, ooh-ooh<br/>Jeongdabi anira haedo<br/>"
		},
		{
			"id": 25,
			"name_category": "ENHYPEN BEST SONG",
			"title": "UPEER SIDE DREAMIN",
			"image": "file:///android_asset/image/anyar.jpg",
			"link_mp3": "mp3/UPEERSIDEDREAMIN.mp3",
			"duration": "205",
			"lyrics": "<br/>Hanyeoreum bamui dream<br/>Addicted to the summer nights<br/><br/>Eodum sogeul mikkeureojyeo dallyeogago isseo<br/>Yeoreumbam we riding aboard<br/>Deo wiro deo wiro we dream on<br/>I gose omyeon geori wiro<br/>Fancy car, a big house<br/>Hyanggijocha dallajin deuthae<br/>Kkumgyeolcheoreom uril bangine<br/>Let's have some fun some fun<br/><br/>Uptown girls are smiling<br/>Illeongineun bulbit<br/>Budeureopge nareul chodaehaji<br/>Haneulbichui river view<br/>Daeul geonman gateun geol<br/>Kkumui kkumeuro nan ride<br/><br/>Ajjilhan du-ru-ru-ru-ru-ru-ru<br/>Upper side dreamin' yeah<br/>Naraoreuge hae<br/>Kkumeul igose dugo gara hae<br/>Dasi du-ru-ru-ru-ru-ru-ru<br/>Sangsanghae clearly<br/>Ayy kkumeun hyeonsiri dwae<br/>Nareul gidaryeo jul ge bunmyeonghae<br/><br/>Hanyeoreum bamui dream (Summer night, summer night)<br/>My dream (Summer night)<br/>Hanyeoreum bamui dream (Summer night, summer night)<br/>My dream (Summer night)<br/>Hanyeoreum bamui dream<br/><br/>TVe deureoon deut<br/>Everything's so fancy<br/>Modeun saramdeul<br/>Yeoyuroun pyojeong useo useo<br/>Geujeo modeun ge bureowo reowo<br/>Eosaekajiman nan waenji<br/>Isseoya hal goseul chajeun geot gata<br/>Ha-ha-ha-ha<br/><br/>Rooftop bulbit arae<br/>Gyeongkwaehan champagne glass<br/>Mongnonghaejyeo ganeun gyeonggye soge<br/>Dalkomhan i punggyeonge<br/>Seokkin geonman gateungeol<br/>Kkumui kkumeuro nan ride<br/><br/>Ajjilhan du-ru-ru-ru-ru-ru-ru<br/>Upper side dreamin' yeah<br/>Naraoreuge hae<br/>Kkumeul igose dugo gara hae<br/>Dasi du-ru-ru-ru-ru-ru-ru<br/>Sangsanghae clearly<br/>Ayy kkumeun hyeonsiri dwae<br/>Nareul gidaryeo jul ge bunmyeonghae<br/><br/>Hanyeoreum bamui dream (Summer night, Summer night)<br/>My dream (Summer night)<br/>Hanyeoreum bamui dream (Summer night, summer night)<br/>My dream (Summer night)<br/>Hanyeoreum bamui dream<br/><br/>Hoksina sarajilkka bwa<br/>Hoksina sarajilkka bwa<br/>Hoksina sarajilkka bwa<br/>Hoksina hoksina<br/>Hoksina sarajilkka bwa<br/><br/>Adeukan du-ru-ru-ru-ru-ru-ru<br/>Upper side dreamin' yeah<br/>Jakku dwidorabwa yeah<br/>Kkaeji anneun geu kkumeul kkuryeo hae<br/>Dasi du-ru-ru-ru-ru-ru-ru<br/>Sangsanghae clearly<br/>Ayy kkumeun hyeonsiri dwae<br/>Nareul gidaryeo jul ge bunmyeonghae<br/><br/>Hanyeoreum bamui dream (Summer night, Summer night)<br/>My dream (Summer night)<br/>Hanyeoreum bamui dream (Summer night, summer night)<br/>My dream (Summer night)<br/>Hanyeoreum bamui dream<br/>"
		},
		{
			"id": 26,
			"name_category": "ENHYPEN BEST SONG",
			"title": "Very Good",
			"image": "file:///android_asset/image/anyar.jpg",
			"link_mp3": "mp3/VeryGood.mp3",
			"duration": "203",
			"lyrics": "<br/>Guess who's back?<br/>Ayo Pop, we did it again, man<br/>Aight do, let's go<br/><br/>Show time<br/>Hwanhowa gidae soge cheot deungjang<br/>No doubt<br/>Namdeulgwa chabyeolhwadoeneun sungan<br/>Nagal muneun eopseo<br/>Neon neoksi nagage dwae<br/>Getcha, getcha ya ya here<br/>Getcha, getcha ya ya<br/>Get on<br/>Rock 'n' roll<br/><br/>I'm very, very good<br/>I wanna rock right now<br/>I wanna rock right now<br/>I wanna rock right now<br/>I wanna rock right now<br/>Very, very good<br/>I wanna rock right now<br/>I wanna rock right now<br/><br/>King of the jungle<br/>Kkomadeul jaerongjanchireul meomchwo<br/>Bunwigineun beolsseo mureuigeotgo<br/>Sunsikgane gaekseogeul jeongbok<br/>Kapeseul kkara henggarae bada<br/>Teojineun pop bottle<br/>Bakchareul gahae<br/>How many fake MCs out there? (Turn up)<br/><br/>Beoldeura deo sege ureo wengweng<br/>Mudaega tteonagage bimyeong jilleo ttaekttaek<br/>Amuna deryeo osigo<br/>Maeum naekineun daero umjingnyeo<br/>Getcha, getcha ya ya here<br/>Getcha, getcha ya ya<br/>Get on<br/>Sigan da dwaesseo jeongjeogeul kkaewo<br/>Jeokdanghi hal saenggak beoryeo stupid<br/>Eomjireul sewo yeolgireul bultaewo<br/>I guyeogui michinnomdeul moyeora<br/><br/>I'm very, very good<br/>I wanna rock right now<br/>I wanna rock right now<br/>I wanna rock right now<br/>I wanna rock right now<br/>Very, very good<br/>I wanna rock right now<br/>I wanna rock right now<br/><br/>An naomyeon chyeodeureoganda<br/>Jo joyeo deureoganda<br/>An naomyeon chyeodeureoganda<br/>What can I do for you? Huh<br/>An naomyeon chyeodeureoganda<br/>Jo joyeo deureoganda<br/>An naomyeon chyeodeureoganda<br/>Aight<br/><br/>Pokju haneun ilgop akdang<br/>Ppalgan bulloneun mot maga<br/>Nae miteuro jumok handa<br/>Jeonbange himchan hamseong balsa<br/>Hey geogi neo ttong pom japjima<br/>Sondeureo beol jom batja<br/>Hanaga doen deusi danhabeul hae<br/>Make some noise<br/><br/>Beoldeura deo sege ureo wengweng<br/>Mudaega tteonagage bimyeong jilleo ttaekttaek<br/>Kkonminamdeureun gireul sseo<br/>Sen cheok haedo neomu gwiyeoungeol<br/>Kkaengpan buryeo gaepan 5bunjeon<br/>Ireon keonsebeun<br/>Uriga jeonmuniya leggo<br/>Sigan da dwaesseo jeongjeogeul kkaewo<br/>Jeokdanghi hal saenggakdeureun gatdabeoryeo stupid<br/>Eomjireul sewo yeolgireul bultaewo<br/>I guyeogui michinnomdeul moyeora<br/><br/>I'm very, very good<br/>Are you ready?<br/>I'm very, very good<br/>I wanna rock right now<br/>I wanna rock right now<br/>I wanna rock right now<br/>I wanna rock right now<br/>Very, very good<br/>I wanna rock right now<br/>I wanna rock right now<br/>"
		}
		
		

	]
}
